{"expand":"renderedFields,names,schema,operations,editmeta,changelog,versionedRepresentations","id":"12548873","self":"https://issues.apache.org/jira/rest/api/2/issue/12548873","key":"MAPREDUCE-4091","fields":{"issuetype":{"self":"https://issues.apache.org/jira/rest/api/2/issuetype/1","id":"1","description":"A problem which impairs or prevents the functions of the product.","iconUrl":"https://issues.apache.org/jira/secure/viewavatar?size=xsmall&avatarId=21133&avatarType=issuetype","name":"Bug","subtask":false,"avatarId":21133},"timespent":null,"project":{"self":"https://issues.apache.org/jira/rest/api/2/project/12310941","id":"12310941","key":"MAPREDUCE","name":"Hadoop Map/Reduce","avatarUrls":{"48x48":"https://issues.apache.org/jira/secure/projectavatar?pid=12310941&avatarId=10096","24x24":"https://issues.apache.org/jira/secure/projectavatar?size=small&pid=12310941&avatarId=10096","16x16":"https://issues.apache.org/jira/secure/projectavatar?size=xsmall&pid=12310941&avatarId=10096","32x32":"https://issues.apache.org/jira/secure/projectavatar?size=medium&pid=12310941&avatarId=10096"},"projectCategory":{"self":"https://issues.apache.org/jira/rest/api/2/projectCategory/10292","id":"10292","description":"Scalable Distributed Computing","name":"Hadoop"}},"fixVersions":[{"self":"https://issues.apache.org/jira/rest/api/2/version/12320060","id":"12320060","description":"0.23.3","name":"0.23.3","archived":false,"released":true,"releaseDate":"2012-09-20"},{"self":"https://issues.apache.org/jira/rest/api/2/version/12322471","id":"12322471","description":"2.0.2-alpha release","name":"2.0.2-alpha","archived":false,"released":true,"releaseDate":"2012-10-09"}],"aggregatetimespent":null,"resolution":{"self":"https://issues.apache.org/jira/rest/api/2/resolution/1","id":"1","description":"A fix for this issue is checked into the tree and tested.","name":"Fixed"},"customfield_12312322":null,"customfield_12310220":"2012-03-30T21:25:49.653+0000","customfield_12312520":null,"customfield_12312323":null,"customfield_12312521":"Tue Aug 21 12:41:06 UTC 2012","customfield_12310420":"233970","customfield_12312320":null,"customfield_12310222":"10002_*:*_1_*:*_1037151_*|*_1_*:*_1_*:*_383799_*|*_5_*:*_1_*:*_0","customfield_12312321":null,"resolutiondate":"2012-03-30T21:32:28.481+0000","workratio":-1,"customfield_12312328":null,"customfield_12312329":null,"customfield_12312923":null,"customfield_12312326":null,"customfield_12312920":null,"customfield_12310300":null,"customfield_12312327":null,"customfield_12312921":null,"customfield_12312324":null,"customfield_12312720":null,"customfield_12312325":null,"lastViewed":null,"watches":{"self":"https://issues.apache.org/jira/rest/api/2/issue/MAPREDUCE-4091/watchers","watchCount":3,"isWatching":false},"created":"2012-03-30T21:08:47.587+0000","customfield_12310192":null,"customfield_12310191":[{"self":"https://issues.apache.org/jira/rest/api/2/customFieldOption/10343","value":"Reviewed","id":"10343"}],"priority":{"self":"https://issues.apache.org/jira/rest/api/2/priority/2","iconUrl":"https://issues.apache.org/jira/images/icons/priorities/critical.svg","name":"Critical","id":"2"},"labels":[],"customfield_12312333":null,"customfield_12310230":null,"customfield_12312334":null,"customfield_12313422":"false","customfield_12310310":"1.0","customfield_12312331":null,"customfield_12312332":null,"timeestimate":null,"aggregatetimeoriginalestimate":null,"customfield_12311120":null,"customfield_12312330":null,"versions":[{"self":"https://issues.apache.org/jira/rest/api/2/version/12320354","id":"12320354","description":"hadoop-2.0.0-alpha release","name":"2.0.0-alpha","archived":false,"released":true,"releaseDate":"2012-05-23"}],"issuelinks":[],"customfield_12312339":null,"assignee":{"self":"https://issues.apache.org/jira/rest/api/2/user?username=tucu00","name":"tucu00","key":"tucu00","avatarUrls":{"48x48":"https://issues.apache.org/jira/secure/useravatar?avatarId=10452","24x24":"https://issues.apache.org/jira/secure/useravatar?size=small&avatarId=10452","16x16":"https://issues.apache.org/jira/secure/useravatar?size=xsmall&avatarId=10452","32x32":"https://issues.apache.org/jira/secure/useravatar?size=medium&avatarId=10452"},"displayName":"Alejandro Abdelnur","active":true,"timeZone":"Europe/Madrid"},"customfield_12312337":null,"customfield_12312338":null,"updated":"2012-09-07T21:03:36.542+0000","customfield_12312335":null,"customfield_12312336":null,"status":{"self":"https://issues.apache.org/jira/rest/api/2/status/6","description":"The issue is considered finished, the resolution is correct. Issues which are not closed can be reopened.","iconUrl":"https://issues.apache.org/jira/images/icons/statuses/closed.png","name":"Closed","id":"6","statusCategory":{"self":"https://issues.apache.org/jira/rest/api/2/statuscategory/3","id":3,"key":"done","colorName":"green","name":"Done"}},"components":[{"self":"https://issues.apache.org/jira/rest/api/2/component/12312909","id":"12312909","name":"build"},{"self":"https://issues.apache.org/jira/rest/api/2/component/12312904","id":"12312904","name":"test"}],"timeoriginalestimate":null,"description":"MAPREDUCE-4082 moved the generated-classpath file used by MRApp from the main classpath to the test classpath.\n\nThe objective of MAPREDUCE-4082 was to remove the generated-classpath file from the hadoop-mapreduce-client-app JAR. I've thought that moving it to the test-classpath would do the trick.\n\nThis is breaking tools testcases (most likely) because of different classloader being used by maven for main classpath and test classpath.\n\n","customfield_10010":null,"timetracking":{},"customfield_12312026":null,"customfield_12312023":null,"customfield_12310320":null,"customfield_12312024":null,"customfield_12312340":null,"attachment":[{"self":"https://issues.apache.org/jira/rest/api/2/attachment/12520672","id":"12520672","filename":"MAPREDUCE-4091.patch","author":{"self":"https://issues.apache.org/jira/rest/api/2/user?username=tucu00","name":"tucu00","key":"tucu00","avatarUrls":{"48x48":"https://issues.apache.org/jira/secure/useravatar?avatarId=10452","24x24":"https://issues.apache.org/jira/secure/useravatar?size=small&avatarId=10452","16x16":"https://issues.apache.org/jira/secure/useravatar?size=xsmall&avatarId=10452","32x32":"https://issues.apache.org/jira/secure/useravatar?size=medium&avatarId=10452"},"displayName":"Alejandro Abdelnur","active":true,"timeZone":"Europe/Madrid"},"created":"2012-03-30T21:15:00.182+0000","size":1099,"mimeType":"text/plain","content":"https://issues.apache.org/jira/secure/attachment/12520672/MAPREDUCE-4091.patch"}],"aggregatetimeestimate":null,"customfield_12312341":null,"customfield_12312220":null,"customfield_12312022":null,"customfield_12310921":null,"customfield_12310920":"44317","customfield_12312823":null,"summary":"tools testcases failing because of MAPREDUCE-4082","creator":{"self":"https://issues.apache.org/jira/rest/api/2/user?username=tucu00","name":"tucu00","key":"tucu00","avatarUrls":{"48x48":"https://issues.apache.org/jira/secure/useravatar?avatarId=10452","24x24":"https://issues.apache.org/jira/secure/useravatar?size=small&avatarId=10452","16x16":"https://issues.apache.org/jira/secure/useravatar?size=xsmall&avatarId=10452","32x32":"https://issues.apache.org/jira/secure/useravatar?size=medium&avatarId=10452"},"displayName":"Alejandro Abdelnur","active":true,"timeZone":"Europe/Madrid"},"subtasks":[],"customfield_12310291":null,"reporter":{"self":"https://issues.apache.org/jira/rest/api/2/user?username=tucu00","name":"tucu00","key":"tucu00","avatarUrls":{"48x48":"https://issues.apache.org/jira/secure/useravatar?avatarId=10452","24x24":"https://issues.apache.org/jira/secure/useravatar?size=small&avatarId=10452","16x16":"https://issues.apache.org/jira/secure/useravatar?size=xsmall&avatarId=10452","32x32":"https://issues.apache.org/jira/secure/useravatar?size=medium&avatarId=10452"},"displayName":"Alejandro Abdelnur","active":true,"timeZone":"Europe/Madrid"},"customfield_12310290":null,"aggregateprogress":{"progress":0,"total":0},"customfield_12311024":null,"environment":null,"customfield_12313520":null,"customfield_12311020":null,"duedate":null,"customfield_12310250":null,"progress":{"progress":0,"total":0},"comment":{"comments":[{"self":"https://issues.apache.org/jira/rest/api/2/issue/12548873/comment/13242749","id":"13242749","author":{"self":"https://issues.apache.org/jira/rest/api/2/user?username=tucu00","name":"tucu00","key":"tucu00","avatarUrls":{"48x48":"https://issues.apache.org/jira/secure/useravatar?avatarId=10452","24x24":"https://issues.apache.org/jira/secure/useravatar?size=small&avatarId=10452","16x16":"https://issues.apache.org/jira/secure/useravatar?size=xsmall&avatarId=10452","32x32":"https://issues.apache.org/jira/secure/useravatar?size=medium&avatarId=10452"},"displayName":"Alejandro Abdelnur","active":true,"timeZone":"Europe/Madrid"},"body":"The generated-classpath file has a meaning for running testcases in the current project. If downstream projects want to leverage that file, they have create it in their project (i.e. oozie-core creates one to be able to use MiniMR).\n\nHaving the generated-classpath file bundled in the JAR is pointless, and as MAPREDUCE-4082 stated, pollutes the classpath big time.\n\nAn alternate way to achieve not having the generated-classpath file in the JAR is to excluded it in the maven-jar-plugin.\n","updateAuthor":{"self":"https://issues.apache.org/jira/rest/api/2/user?username=tucu00","name":"tucu00","key":"tucu00","avatarUrls":{"48x48":"https://issues.apache.org/jira/secure/useravatar?avatarId=10452","24x24":"https://issues.apache.org/jira/secure/useravatar?size=small&avatarId=10452","16x16":"https://issues.apache.org/jira/secure/useravatar?size=xsmall&avatarId=10452","32x32":"https://issues.apache.org/jira/secure/useravatar?size=medium&avatarId=10452"},"displayName":"Alejandro Abdelnur","active":true,"timeZone":"Europe/Madrid"},"created":"2012-03-30T21:12:18.037+0000","updated":"2012-03-30T21:12:18.037+0000"},{"self":"https://issues.apache.org/jira/rest/api/2/issue/12548873/comment/13242756","id":"13242756","author":{"self":"https://issues.apache.org/jira/rest/api/2/user?username=tucu00","name":"tucu00","key":"tucu00","avatarUrls":{"48x48":"https://issues.apache.org/jira/secure/useravatar?avatarId=10452","24x24":"https://issues.apache.org/jira/secure/useravatar?size=small&avatarId=10452","16x16":"https://issues.apache.org/jira/secure/useravatar?size=xsmall&avatarId=10452","32x32":"https://issues.apache.org/jira/secure/useravatar?size=medium&avatarId=10452"},"displayName":"Alejandro Abdelnur","active":true,"timeZone":"Europe/Madrid"},"body":"the tools (streaming & archives) failing testcases are passing again.\n\nand the hadoop-mapreduce-client-app JAR does not have the mrapp-generated-classpath file in it.","updateAuthor":{"self":"https://issues.apache.org/jira/rest/api/2/user?username=tucu00","name":"tucu00","key":"tucu00","avatarUrls":{"48x48":"https://issues.apache.org/jira/secure/useravatar?avatarId=10452","24x24":"https://issues.apache.org/jira/secure/useravatar?size=small&avatarId=10452","16x16":"https://issues.apache.org/jira/secure/useravatar?size=xsmall&avatarId=10452","32x32":"https://issues.apache.org/jira/secure/useravatar?size=medium&avatarId=10452"},"displayName":"Alejandro Abdelnur","active":true,"timeZone":"Europe/Madrid"},"created":"2012-03-30T21:15:00.242+0000","updated":"2012-03-30T21:15:00.242+0000"},{"self":"https://issues.apache.org/jira/rest/api/2/issue/12548873/comment/13242760","id":"13242760","author":{"self":"https://issues.apache.org/jira/rest/api/2/user?username=mahadev","name":"mahadev","key":"mahadev","avatarUrls":{"48x48":"https://issues.apache.org/jira/secure/useravatar?avatarId=10452","24x24":"https://issues.apache.org/jira/secure/useravatar?size=small&avatarId=10452","16x16":"https://issues.apache.org/jira/secure/useravatar?size=xsmall&avatarId=10452","32x32":"https://issues.apache.org/jira/secure/useravatar?size=medium&avatarId=10452"},"displayName":"Mahadev konar","active":true,"timeZone":"Etc/UTC"},"body":"+1 for the patch. Looks good.","updateAuthor":{"self":"https://issues.apache.org/jira/rest/api/2/user?username=mahadev","name":"mahadev","key":"mahadev","avatarUrls":{"48x48":"https://issues.apache.org/jira/secure/useravatar?avatarId=10452","24x24":"https://issues.apache.org/jira/secure/useravatar?size=small&avatarId=10452","16x16":"https://issues.apache.org/jira/secure/useravatar?size=xsmall&avatarId=10452","32x32":"https://issues.apache.org/jira/secure/useravatar?size=medium&avatarId=10452"},"displayName":"Mahadev konar","active":true,"timeZone":"Etc/UTC"},"created":"2012-03-30T21:25:49.653+0000","updated":"2012-03-30T21:25:49.653+0000"},{"self":"https://issues.apache.org/jira/rest/api/2/issue/12548873/comment/13242765","id":"13242765","author":{"self":"https://issues.apache.org/jira/rest/api/2/user?username=tucu00","name":"tucu00","key":"tucu00","avatarUrls":{"48x48":"https://issues.apache.org/jira/secure/useravatar?avatarId=10452","24x24":"https://issues.apache.org/jira/secure/useravatar?size=small&avatarId=10452","16x16":"https://issues.apache.org/jira/secure/useravatar?size=xsmall&avatarId=10452","32x32":"https://issues.apache.org/jira/secure/useravatar?size=medium&avatarId=10452"},"displayName":"Alejandro Abdelnur","active":true,"timeZone":"Europe/Madrid"},"body":"committed to trunk & branch-2","updateAuthor":{"self":"https://issues.apache.org/jira/rest/api/2/user?username=tucu00","name":"tucu00","key":"tucu00","avatarUrls":{"48x48":"https://issues.apache.org/jira/secure/useravatar?avatarId=10452","24x24":"https://issues.apache.org/jira/secure/useravatar?size=small&avatarId=10452","16x16":"https://issues.apache.org/jira/secure/useravatar?size=xsmall&avatarId=10452","32x32":"https://issues.apache.org/jira/secure/useravatar?size=medium&avatarId=10452"},"displayName":"Alejandro Abdelnur","active":true,"timeZone":"Europe/Madrid"},"created":"2012-03-30T21:32:28.530+0000","updated":"2012-03-30T21:32:28.530+0000"},{"self":"https://issues.apache.org/jira/rest/api/2/issue/12548873/comment/13242771","id":"13242771","author":{"self":"https://issues.apache.org/jira/rest/api/2/user?username=hudson","name":"hudson","key":"hudson","avatarUrls":{"48x48":"https://issues.apache.org/jira/secure/useravatar?avatarId=10452","24x24":"https://issues.apache.org/jira/secure/useravatar?size=small&avatarId=10452","16x16":"https://issues.apache.org/jira/secure/useravatar?size=xsmall&avatarId=10452","32x32":"https://issues.apache.org/jira/secure/useravatar?size=medium&avatarId=10452"},"displayName":"Hudson","active":true,"timeZone":"Etc/UTC"},"body":"Integrated in Hadoop-Hdfs-trunk-Commit #2031 (See [https://builds.apache.org/job/Hadoop-Hdfs-trunk-Commit/2031/])\n    MAPREDUCE-4091. tools testcases failing because of MAPREDUCE-4082 (tucu) (Revision 1307623)\n\n     Result = SUCCESS\ntucu : http://svn.apache.org/viewcvs.cgi/?root=Apache-SVN&view=rev&rev=1307623\nFiles : \n* /hadoop/common/trunk/hadoop-mapreduce-project/CHANGES.txt\n* /hadoop/common/trunk/hadoop-mapreduce-project/hadoop-mapreduce-client/hadoop-mapreduce-client-app/pom.xml\n","updateAuthor":{"self":"https://issues.apache.org/jira/rest/api/2/user?username=hudson","name":"hudson","key":"hudson","avatarUrls":{"48x48":"https://issues.apache.org/jira/secure/useravatar?avatarId=10452","24x24":"https://issues.apache.org/jira/secure/useravatar?size=small&avatarId=10452","16x16":"https://issues.apache.org/jira/secure/useravatar?size=xsmall&avatarId=10452","32x32":"https://issues.apache.org/jira/secure/useravatar?size=medium&avatarId=10452"},"displayName":"Hudson","active":true,"timeZone":"Etc/UTC"},"created":"2012-03-30T21:35:53.654+0000","updated":"2012-03-30T21:35:53.654+0000"},{"self":"https://issues.apache.org/jira/rest/api/2/issue/12548873/comment/13242775","id":"13242775","author":{"self":"https://issues.apache.org/jira/rest/api/2/user?username=hudson","name":"hudson","key":"hudson","avatarUrls":{"48x48":"https://issues.apache.org/jira/secure/useravatar?avatarId=10452","24x24":"https://issues.apache.org/jira/secure/useravatar?size=small&avatarId=10452","16x16":"https://issues.apache.org/jira/secure/useravatar?size=xsmall&avatarId=10452","32x32":"https://issues.apache.org/jira/secure/useravatar?size=medium&avatarId=10452"},"displayName":"Hudson","active":true,"timeZone":"Etc/UTC"},"body":"Integrated in Hadoop-Common-trunk-Commit #1956 (See [https://builds.apache.org/job/Hadoop-Common-trunk-Commit/1956/])\n    MAPREDUCE-4091. tools testcases failing because of MAPREDUCE-4082 (tucu) (Revision 1307623)\n\n     Result = SUCCESS\ntucu : http://svn.apache.org/viewcvs.cgi/?root=Apache-SVN&view=rev&rev=1307623\nFiles : \n* /hadoop/common/trunk/hadoop-mapreduce-project/CHANGES.txt\n* /hadoop/common/trunk/hadoop-mapreduce-project/hadoop-mapreduce-client/hadoop-mapreduce-client-app/pom.xml\n","updateAuthor":{"self":"https://issues.apache.org/jira/rest/api/2/user?username=hudson","name":"hudson","key":"hudson","avatarUrls":{"48x48":"https://issues.apache.org/jira/secure/useravatar?avatarId=10452","24x24":"https://issues.apache.org/jira/secure/useravatar?size=small&avatarId=10452","16x16":"https://issues.apache.org/jira/secure/useravatar?size=xsmall&avatarId=10452","32x32":"https://issues.apache.org/jira/secure/useravatar?size=medium&avatarId=10452"},"displayName":"Hudson","active":true,"timeZone":"Etc/UTC"},"created":"2012-03-30T21:37:54.115+0000","updated":"2012-03-30T21:37:54.115+0000"},{"self":"https://issues.apache.org/jira/rest/api/2/issue/12548873/comment/13242808","id":"13242808","author":{"self":"https://issues.apache.org/jira/rest/api/2/user?username=hudson","name":"hudson","key":"hudson","avatarUrls":{"48x48":"https://issues.apache.org/jira/secure/useravatar?avatarId=10452","24x24":"https://issues.apache.org/jira/secure/useravatar?size=small&avatarId=10452","16x16":"https://issues.apache.org/jira/secure/useravatar?size=xsmall&avatarId=10452","32x32":"https://issues.apache.org/jira/secure/useravatar?size=medium&avatarId=10452"},"displayName":"Hudson","active":true,"timeZone":"Etc/UTC"},"body":"Integrated in Hadoop-Mapreduce-trunk-Commit #1969 (See [https://builds.apache.org/job/Hadoop-Mapreduce-trunk-Commit/1969/])\n    MAPREDUCE-4091. tools testcases failing because of MAPREDUCE-4082 (tucu) (Revision 1307623)\n\n     Result = ABORTED\ntucu : http://svn.apache.org/viewcvs.cgi/?root=Apache-SVN&view=rev&rev=1307623\nFiles : \n* /hadoop/common/trunk/hadoop-mapreduce-project/CHANGES.txt\n* /hadoop/common/trunk/hadoop-mapreduce-project/hadoop-mapreduce-client/hadoop-mapreduce-client-app/pom.xml\n","updateAuthor":{"self":"https://issues.apache.org/jira/rest/api/2/user?username=hudson","name":"hudson","key":"hudson","avatarUrls":{"48x48":"https://issues.apache.org/jira/secure/useravatar?avatarId=10452","24x24":"https://issues.apache.org/jira/secure/useravatar?size=small&avatarId=10452","16x16":"https://issues.apache.org/jira/secure/useravatar?size=xsmall&avatarId=10452","32x32":"https://issues.apache.org/jira/secure/useravatar?size=medium&avatarId=10452"},"displayName":"Hudson","active":true,"timeZone":"Etc/UTC"},"created":"2012-03-30T22:17:27.555+0000","updated":"2012-03-30T22:17:27.555+0000"},{"self":"https://issues.apache.org/jira/rest/api/2/issue/12548873/comment/13242827","id":"13242827","author":{"self":"https://issues.apache.org/jira/rest/api/2/user?username=hadoopqa","name":"hadoopqa","key":"hadoopqa","avatarUrls":{"48x48":"https://issues.apache.org/jira/secure/useravatar?ownerId=hadoopqa&avatarId=10393","24x24":"https://issues.apache.org/jira/secure/useravatar?size=small&ownerId=hadoopqa&avatarId=10393","16x16":"https://issues.apache.org/jira/secure/useravatar?size=xsmall&ownerId=hadoopqa&avatarId=10393","32x32":"https://issues.apache.org/jira/secure/useravatar?size=medium&ownerId=hadoopqa&avatarId=10393"},"displayName":"Hadoop QA","active":true,"timeZone":"Etc/UTC"},"body":"-1 overall.  Here are the results of testing the latest attachment \n  http://issues.apache.org/jira/secure/attachment/12520672/MAPREDUCE-4091.patch\n  against trunk revision .\n\n    +1 @author.  The patch does not contain any @author tags.\n\n    +1 tests included.  The patch appears to include 1 new or modified tests.\n\n    +1 javadoc.  The javadoc tool did not generate any warning messages.\n\n    +1 javac.  The applied patch does not increase the total number of javac compiler warnings.\n\n    +1 eclipse:eclipse.  The patch built with eclipse:eclipse.\n\n    +1 findbugs.  The patch does not introduce any new Findbugs (version 1.3.9) warnings.\n\n    +1 release audit.  The applied patch does not increase the total number of release audit warnings.\n\n    -1 core tests.  The patch failed these unit tests:\n                  org.apache.hadoop.mapreduce.v2.TestMRJobs\n                  org.apache.hadoop.mapred.TestMiniMRBringup\n                  org.apache.hadoop.mapred.TestMiniMRChildTask\n                  org.apache.hadoop.mapred.TestReduceFetch\n                  org.apache.hadoop.mapred.TestReduceFetchFromPartialMem\n                  org.apache.hadoop.mapred.TestJobCounters\n                  org.apache.hadoop.mapreduce.TestChild\n                  org.apache.hadoop.mapred.TestMiniMRClientCluster\n                  org.apache.hadoop.mapreduce.v2.TestMROldApiJobs\n                  org.apache.hadoop.mapreduce.v2.TestSpeculativeExecution\n                  org.apache.hadoop.mapreduce.lib.output.TestJobOutputCommitter\n                  org.apache.hadoop.mapred.TestClientRedirect\n                  org.apache.hadoop.mapred.TestLazyOutput\n                  org.apache.hadoop.mapred.TestJobCleanup\n                  org.apache.hadoop.mapreduce.TestMapReduceLazyOutput\n                  org.apache.hadoop.mapred.TestSpecialCharactersInOutputPath\n                  org.apache.hadoop.mapreduce.v2.TestRMNMInfo\n                  org.apache.hadoop.mapreduce.v2.TestNonExistentJob\n                  org.apache.hadoop.mapred.TestJobSysDirWithDFS\n                  org.apache.hadoop.mapreduce.v2.TestUberAM\n                  org.apache.hadoop.mapreduce.v2.TestMiniMRProxyUser\n                  org.apache.hadoop.mapreduce.security.TestJHSSecurity\n\n    +1 contrib tests.  The patch passed contrib unit tests.\n\nTest results: https://builds.apache.org/job/PreCommit-MAPREDUCE-Build/2120//testReport/\nConsole output: https://builds.apache.org/job/PreCommit-MAPREDUCE-Build/2120//console\n\nThis message is automatically generated.","updateAuthor":{"self":"https://issues.apache.org/jira/rest/api/2/user?username=hadoopqa","name":"hadoopqa","key":"hadoopqa","avatarUrls":{"48x48":"https://issues.apache.org/jira/secure/useravatar?ownerId=hadoopqa&avatarId=10393","24x24":"https://issues.apache.org/jira/secure/useravatar?size=small&ownerId=hadoopqa&avatarId=10393","16x16":"https://issues.apache.org/jira/secure/useravatar?size=xsmall&ownerId=hadoopqa&avatarId=10393","32x32":"https://issues.apache.org/jira/secure/useravatar?size=medium&ownerId=hadoopqa&avatarId=10393"},"displayName":"Hadoop QA","active":true,"timeZone":"Etc/UTC"},"created":"2012-03-30T22:48:43.898+0000","updated":"2012-03-30T22:48:43.898+0000"},{"self":"https://issues.apache.org/jira/rest/api/2/issue/12548873/comment/13243131","id":"13243131","author":{"self":"https://issues.apache.org/jira/rest/api/2/user?username=hudson","name":"hudson","key":"hudson","avatarUrls":{"48x48":"https://issues.apache.org/jira/secure/useravatar?avatarId=10452","24x24":"https://issues.apache.org/jira/secure/useravatar?size=small&avatarId=10452","16x16":"https://issues.apache.org/jira/secure/useravatar?size=xsmall&avatarId=10452","32x32":"https://issues.apache.org/jira/secure/useravatar?size=medium&avatarId=10452"},"displayName":"Hudson","active":true,"timeZone":"Etc/UTC"},"body":"Integrated in Hadoop-Hdfs-trunk #1001 (See [https://builds.apache.org/job/Hadoop-Hdfs-trunk/1001/])\n    MAPREDUCE-4091. tools testcases failing because of MAPREDUCE-4082 (tucu) (Revision 1307623)\n\n     Result = FAILURE\ntucu : http://svn.apache.org/viewcvs.cgi/?root=Apache-SVN&view=rev&rev=1307623\nFiles : \n* /hadoop/common/trunk/hadoop-mapreduce-project/CHANGES.txt\n* /hadoop/common/trunk/hadoop-mapreduce-project/hadoop-mapreduce-client/hadoop-mapreduce-client-app/pom.xml\n","updateAuthor":{"self":"https://issues.apache.org/jira/rest/api/2/user?username=hudson","name":"hudson","key":"hudson","avatarUrls":{"48x48":"https://issues.apache.org/jira/secure/useravatar?avatarId=10452","24x24":"https://issues.apache.org/jira/secure/useravatar?size=small&avatarId=10452","16x16":"https://issues.apache.org/jira/secure/useravatar?size=xsmall&avatarId=10452","32x32":"https://issues.apache.org/jira/secure/useravatar?size=medium&avatarId=10452"},"displayName":"Hudson","active":true,"timeZone":"Etc/UTC"},"created":"2012-03-31T13:01:32.970+0000","updated":"2012-03-31T13:01:32.970+0000"},{"self":"https://issues.apache.org/jira/rest/api/2/issue/12548873/comment/13243155","id":"13243155","author":{"self":"https://issues.apache.org/jira/rest/api/2/user?username=hudson","name":"hudson","key":"hudson","avatarUrls":{"48x48":"https://issues.apache.org/jira/secure/useravatar?avatarId=10452","24x24":"https://issues.apache.org/jira/secure/useravatar?size=small&avatarId=10452","16x16":"https://issues.apache.org/jira/secure/useravatar?size=xsmall&avatarId=10452","32x32":"https://issues.apache.org/jira/secure/useravatar?size=medium&avatarId=10452"},"displayName":"Hudson","active":true,"timeZone":"Etc/UTC"},"body":"Integrated in Hadoop-Mapreduce-trunk #1036 (See [https://builds.apache.org/job/Hadoop-Mapreduce-trunk/1036/])\n    MAPREDUCE-4091. tools testcases failing because of MAPREDUCE-4082 (tucu) (Revision 1307623)\n\n     Result = FAILURE\ntucu : http://svn.apache.org/viewcvs.cgi/?root=Apache-SVN&view=rev&rev=1307623\nFiles : \n* /hadoop/common/trunk/hadoop-mapreduce-project/CHANGES.txt\n* /hadoop/common/trunk/hadoop-mapreduce-project/hadoop-mapreduce-client/hadoop-mapreduce-client-app/pom.xml\n","updateAuthor":{"self":"https://issues.apache.org/jira/rest/api/2/user?username=hudson","name":"hudson","key":"hudson","avatarUrls":{"48x48":"https://issues.apache.org/jira/secure/useravatar?avatarId=10452","24x24":"https://issues.apache.org/jira/secure/useravatar?size=small&avatarId=10452","16x16":"https://issues.apache.org/jira/secure/useravatar?size=xsmall&avatarId=10452","32x32":"https://issues.apache.org/jira/secure/useravatar?size=medium&avatarId=10452"},"displayName":"Hudson","active":true,"timeZone":"Etc/UTC"},"created":"2012-03-31T14:12:19.229+0000","updated":"2012-03-31T14:12:19.229+0000"},{"self":"https://issues.apache.org/jira/rest/api/2/issue/12548873/comment/13438131","id":"13438131","author":{"self":"https://issues.apache.org/jira/rest/api/2/user?username=revans2","name":"revans2","key":"revans2","avatarUrls":{"48x48":"https://issues.apache.org/jira/secure/useravatar?avatarId=10452","24x24":"https://issues.apache.org/jira/secure/useravatar?size=small&avatarId=10452","16x16":"https://issues.apache.org/jira/secure/useravatar?size=xsmall&avatarId=10452","32x32":"https://issues.apache.org/jira/secure/useravatar?size=medium&avatarId=10452"},"displayName":"Robert Joseph Evans","active":true,"timeZone":"America/Chicago"},"body":"I pulled this into 0.23.3","updateAuthor":{"self":"https://issues.apache.org/jira/rest/api/2/user?username=revans2","name":"revans2","key":"revans2","avatarUrls":{"48x48":"https://issues.apache.org/jira/secure/useravatar?avatarId=10452","24x24":"https://issues.apache.org/jira/secure/useravatar?size=small&avatarId=10452","16x16":"https://issues.apache.org/jira/secure/useravatar?size=xsmall&avatarId=10452","32x32":"https://issues.apache.org/jira/secure/useravatar?size=medium&avatarId=10452"},"displayName":"Robert Joseph Evans","active":true,"timeZone":"America/Chicago"},"created":"2012-08-20T19:53:04.543+0000","updated":"2012-08-20T19:53:04.543+0000"},{"self":"https://issues.apache.org/jira/rest/api/2/issue/12548873/comment/13438658","id":"13438658","author":{"self":"https://issues.apache.org/jira/rest/api/2/user?username=hudson","name":"hudson","key":"hudson","avatarUrls":{"48x48":"https://issues.apache.org/jira/secure/useravatar?avatarId=10452","24x24":"https://issues.apache.org/jira/secure/useravatar?size=small&avatarId=10452","16x16":"https://issues.apache.org/jira/secure/useravatar?size=xsmall&avatarId=10452","32x32":"https://issues.apache.org/jira/secure/useravatar?size=medium&avatarId=10452"},"displayName":"Hudson","active":true,"timeZone":"Etc/UTC"},"body":"Integrated in Hadoop-Hdfs-0.23-Build #350 (See [https://builds.apache.org/job/Hadoop-Hdfs-0.23-Build/350/])\n    svn merge -c 1307124, 1307623, 1309583 FIXES: MAPREDUCE-4082 MAPREDUCE-4091 and MAPREDUCE-4097 hadoop-mapreduce-client-app's mrapp-generated-classpath file should not be in the module JAR (tucu) (Revision 1375190)\n\n     Result = SUCCESS\nbobby : http://svn.apache.org/viewcvs.cgi/?root=Apache-SVN&view=rev&rev=1375190\nFiles : \n* /hadoop/common/branches/branch-0.23/hadoop-mapreduce-project/CHANGES.txt\n* /hadoop/common/branches/branch-0.23/hadoop-mapreduce-project/hadoop-mapreduce-client/hadoop-mapreduce-client-app/pom.xml\n* /hadoop/common/branches/branch-0.23/hadoop-mapreduce-project/hadoop-mapreduce-client/hadoop-mapreduce-client-common/src/test/java/org/apache/hadoop/mapreduce/v2/util/TestMRApps.java\n* /hadoop/common/branches/branch-0.23/hadoop-project/pom.xml\n","updateAuthor":{"self":"https://issues.apache.org/jira/rest/api/2/user?username=hudson","name":"hudson","key":"hudson","avatarUrls":{"48x48":"https://issues.apache.org/jira/secure/useravatar?avatarId=10452","24x24":"https://issues.apache.org/jira/secure/useravatar?size=small&avatarId=10452","16x16":"https://issues.apache.org/jira/secure/useravatar?size=xsmall&avatarId=10452","32x32":"https://issues.apache.org/jira/secure/useravatar?size=medium&avatarId=10452"},"displayName":"Hudson","active":true,"timeZone":"Etc/UTC"},"created":"2012-08-21T12:41:06.959+0000","updated":"2012-08-21T12:41:06.959+0000"}],"maxResults":12,"total":12,"startAt":0},"votes":{"self":"https://issues.apache.org/jira/rest/api/2/issue/MAPREDUCE-4091/votes","votes":0,"hasVoted":false},"worklog":{"startAt":0,"maxResults":20,"total":0,"worklogs":[]},"customfield_12311820":"0|i07y9b:"}}